Sorting Algorithms/1.BubbleSort/bubble.v
module bubble #(parameter N = 5, parameter width = 8)(
    input clk, rst, start,
    output reg done
);
    reg [width-1:0] A [0:N-1];
    reg [2:0] i, j; // 3-bit for N=5

    always @(posedge clk or posedge rst) begin
        if(rst) begin
            i <= 0; j <= 0; done <= 0;
        end else if (start && !done) begin
            if (i < N-1) begin
                if (j < N-1-i) begin
                    if (A[j] > A[j+1]) begin // > for Ascending
                        A[j]   <= A[j+1];
                        A[j+1] <= A[j]; // Swap works via non-blocking
                    end
                    j <= j + 1;
                end else begin
                    j <= 0;
                    i <= i + 1;
                end
            end else done <= 1;
        end
    end
endmodule

Sorting Algorithms/1.BubbleSort/t_bubble.v
`timescale 1ns/1ps

module t_bubble;
    reg clk, rst, start;
    wire done;

    bubble #(.N(5), .width(8)) uut (
        .clk(clk), .rst(rst), .start(start), .done(done)
    );

    always #5 clk = ~clk;

    initial begin
        $dumpfile("waveform.vcd");
        $dumpvars(0, t_bubble);
        $dumpvars(0, uut.A[0], uut.A[1], uut.A[2], uut.A[3], uut.A[4]);
        
        clk = 0; rst = 1; start = 0;
        
        uut.A[0] = 8'd5;
        uut.A[1] = 8'd12;
        uut.A[2] = 8'd3;
        uut.A[3] = 8'd8;
        uut.A[4] = 8'd1;

        #20 rst = 0; 
        #10 start = 1;

        wait(done);
        #20;
        $finish;
    end
endmodule

Sorting Algorithms/1.BubbleSort/waveform.vcd
$date
	Mon Jan 12 11:30:22 2026
$end
$version
	Icarus Verilog
$end
$timescale
	1ps
$end
$scope module t_bubble $end
$var wire 1 ! done $end
$var reg 1 " clk $end
$var reg 1 # rst $end
$var reg 1 $ start $end
$scope module uut $end
$var wire 1 " clk $end
$var wire 1 # rst $end
$var wire 1 $ start $end
$var parameter 32 % N $end
$var parameter 32 & width $end
$var reg 1 ! done $end
$var reg 3 ' i [2:0] $end
$var reg 3 ( j [2:0] $end
$upscope $end
$upscope $end
$scope module t_bubble $end
$scope module uut $end
$var reg 8 ) \A[0] [7:0] $end
$upscope $end
$upscope $end
$scope module t_bubble $end
$scope module uut $end
$var reg 8 * \A[1] [7:0] $end
$upscope $end
$upscope $end
$scope module t_bubble $end
$scope module uut $end
$var reg 8 + \A[2] [7:0] $end
$upscope $end
$upscope $end
$scope module t_bubble $end
$scope module uut $end
$var reg 8 , \A[3] [7:0] $end
$upscope $end
$upscope $end
$scope module t_bubble $end
$scope module uut $end
$var reg 8 - \A[4] [7:0] $end
$upscope $end
$upscope $end
$enddefinitions $end
$comment Show the parameter values. $end
$dumpall
b1000 &
b101 %
$end
#0
$dumpvars
b1 -
b1000 ,
b11 +
b1100 *
b101 )
b0 (
b0 '
0$
1#
0"
0!
$end
#5000
1"
#10000
0"
#15000
1"
#20000
0"
0#
#25000
1"
#30000
0"
1$
#35000
b1 (
1"
#40000
0"
#45000
b10 (
b1100 +
b11 *
1"
#50000
0"
#55000
b11 (
b1100 ,
b1000 +
1"
#60000
0"
#65000
b100 (
b1100 -
b1 ,
1"
#70000
0"
#75000
b1 '
b0 (
1"
#80000
0"
#85000
b1 (
b101 *
b11 )
1"
#90000
0"
#95000
b10 (
1"
#100000
0"
#105000
b11 (
b1000 ,
b1 +
1"
#110000
0"
#115000
b10 '
b0 (
1"
#120000
0"
#125000
b1 (
1"
#130000
0"
#135000
b10 (
b101 +
b1 *
1"
#140000
0"
#145000
b11 '
b0 (
1"
#150000
0"
#155000
b1 (
b11 *
b1 )
1"
#160000
0"
#165000
b100 '
b0 (
1"
#170000
0"
#175000
1!
1"
